odoo10_addon_customer_outstanding_statement-10.0.1.0.0-py2.7-nspkg.pth
odoo/addons/customer_outstanding_statement/README.rst
odoo/addons/customer_outstanding_statement/__init__.py
odoo/addons/customer_outstanding_statement/__manifest__.py
odoo/addons/customer_outstanding_statement/i18n/ca.po
odoo/addons/customer_outstanding_statement/i18n/de.po
odoo/addons/customer_outstanding_statement/i18n/es.po
odoo/addons/customer_outstanding_statement/i18n/fr.po
odoo/addons/customer_outstanding_statement/i18n/pt.po
odoo/addons/customer_outstanding_statement/report/__init__.py
odoo/addons/customer_outstanding_statement/report/customer_outstanding_statement.py
odoo/addons/customer_outstanding_statement/static/description/Outstanding_Statement.png
odoo/addons/customer_outstanding_statement/static/description/icon.png
odoo/addons/customer_outstanding_statement/static/description/index.html
odoo/addons/customer_outstanding_statement/tests/__init__.py
odoo/addons/customer_outstanding_statement/tests/test_customer_outstanding_statement.py
odoo/addons/customer_outstanding_statement/views/statement.xml
odoo/addons/customer_outstanding_statement/wizard/__init__.py
odoo/addons/customer_outstanding_statement/wizard/customer_outstanding_statement_wizard.py
odoo/addons/customer_outstanding_statement/wizard/customer_outstanding_statement_wizard.xml
odoo10_addon_customer_outstanding_statement-10.0.1.0.0.dist-info/DESCRIPTION.rst
odoo10_addon_customer_outstanding_statement-10.0.1.0.0.dist-info/METADATA
odoo10_addon_customer_outstanding_statement-10.0.1.0.0.dist-info/RECORD
odoo10_addon_customer_outstanding_statement-10.0.1.0.0.dist-info/WHEEL
odoo10_addon_customer_outstanding_statement-10.0.1.0.0.dist-info/metadata.json
odoo10_addon_customer_outstanding_statement-10.0.1.0.0.dist-info/namespace_packages.txt
odoo10_addon_customer_outstanding_statement-10.0.1.0.0.dist-info/top_level.txt
